pydantic_flatten_rootmodel/__init__.py
pydantic_flatten_rootmodel/flatten.py
pydantic_flatten_rootmodel/tests/__init__.py
pydantic_flatten_rootmodel/tests/test_flatten.py
pydantic_flatten_rootmodel-0.1.2.dist-info/LICENSE
pydantic_flatten_rootmodel-0.1.2.dist-info/METADATA
pydantic_flatten_rootmodel-0.1.2.dist-info/WHEEL
pydantic_flatten_rootmodel-0.1.2.dist-info/top_level.txt
pydantic_flatten_rootmodel-0.1.2.dist-info/RECORD
