Metadata-Version: 2.1
Name: pydantic-flatten-rootmodel
Version: 0.1.2
Summary: Library to transform a Pydantic RootModel into a flattened BaseModel
Author-email: Joscha Feth <joscha@planet-a.com>
Classifier: Programming Language :: Python :: 3
Classifier: License :: OSI Approved :: MIT License
Classifier: Operating System :: OS Independent
Requires-Python: >=3.11
License-File: LICENSE
Requires-Dist: pydantic>=2.5.0
